lat_month_inc-1.0.1.dist-info/METADATA
lat_month_inc-1.0.1.dist-info/RECORD
lat_month_inc-1.0.1.dist-info/WHEEL
lat_month_inc-1.0.1.dist-info/top_level.txt
latitude_mon_inc/cal_month_inc.py
